pytouchlinesl/__init__.py
pytouchlinesl/module.py
pytouchlinesl/touchlinesl.py
pytouchlinesl/zone.py
pytouchlinesl/client/__init__.py
pytouchlinesl/client/base.py
pytouchlinesl/client/client.py
pytouchlinesl/client/models/__init__.py
pytouchlinesl/client/models/models.py
pytouchlinesl-0.5.0.dist-info/licenses/LICENSE
pytouchlinesl-0.5.0.dist-info/METADATA
pytouchlinesl-0.5.0.dist-info/WHEEL
pytouchlinesl-0.5.0.dist-info/top_level.txt
pytouchlinesl-0.5.0.dist-info/RECORD
