Metadata-Version: 2.4
Name: pytouchlinesl
Version: 0.5.0
Summary: An API client for Roth's TouchlineSL control system.
Author-email: Jon Seager <jon@sgrs.uk>
Project-URL: Homepage, https://github.com/jnsgruk/pytouchlinesl
Project-URL: Issues, https://github.com/jnsgruk/pytouchlinesl/issues
Classifier: Programming Language :: Python :: 3
Classifier: License :: OSI Approved :: Apache Software License
Classifier: Operating System :: OS Independent
Requires-Python: >=3.10
License-File: LICENSE
Requires-Dist: aiohttp
Requires-Dist: pydantic>=2
Provides-Extra: dev
Requires-Dist: pytest; extra == "dev"
Requires-Dist: pytest-asyncio; extra == "dev"
Requires-Dist: ruff; extra == "dev"
Dynamic: license-file
